despy-1.0.0.dist-info/licenses/LICENSE
simkit/__init__.py
simkit/base.py
simkit/quantiles.py
simkit/rand.py
simkit/simutil.py
simkit/stats.py
simkit/examples/__init__.py
simkit/examples/arrivalprocess.py
simkit/examples/basic.py
simkit/examples/entitycreator.py
simkit/examples/entityserver.py
simkit/examples/finitecapacityqueue.py
simkit/examples/ggkqueue.py
simkit/examples/serverwithreneges.py
simkit/examples/simpleserver.py
simkit/examples/transferline.py
simkit/examples/twocranesberth.py
despy-1.0.0.dist-info/METADATA
despy-1.0.0.dist-info/WHEEL
despy-1.0.0.dist-info/top_level.txt
despy-1.0.0.dist-info/RECORD
