Metadata-Version: 2.4
Name: DESpy
Version: 1.0.0
Summary: Support for DES Modeling using Event Graphs
Home-page: https://github.com/ahbuss/DESpy
Author: Arnold Buss
Author-email: abuss@nps.edu
License: Apache 2.0 License
License-File: LICENSE
Dynamic: author
Dynamic: author-email
Dynamic: description
Dynamic: description-content-type
Dynamic: home-page
Dynamic: license
Dynamic: license-file
Dynamic: summary
